fastchat_hq/__init__.py
fastchat_hq/chat.py
fastchat_hq-0.1.0.dist-info/METADATA
fastchat_hq-0.1.0.dist-info/WHEEL
fastchat_hq-0.1.0.dist-info/licenses/LICENSE
fastchat_hq-0.1.0.dist-info/RECORD
