Metadata-Version: 2.4
Name: fastchat-hq
Version: 0.1.0
Summary: 高性能 OpenAI Chat Completions 异步客户端，支持并发请求、流式响应和批量处理
Project-URL: Homepage, https://github.com/yourusername/fastchat-hq
Project-URL: Repository, https://github.com/yourusername/fastchat-hq
Author-email: Stubblef <tsing967@gmail.com>
License: MIT License
License-File: LICENSE
Keywords: api-client,async,chat,concurrent,openai
Classifier: Development Status :: 3 - Alpha
Classifier: Intended Audience :: Developers
Classifier: Programming Language :: Python :: 3
Classifier: Programming Language :: Python :: 3.10
Classifier: Programming Language :: Python :: 3.11
Classifier: Programming Language :: Python :: 3.12
Requires-Python: >=3.10
Requires-Dist: aiohttp>=3.13.2
Requires-Dist: openai>=2.7.2
